rawls/__init__.py
rawls/rawls.py
rawls/stats.py
rawls/utils.py
rawls/scene/__init__.py
rawls/scene/accelerator.py
rawls/scene/camera.py
rawls/scene/details.py
rawls/scene/film.py
rawls/scene/filter.py
rawls/scene/integrator.py
rawls/scene/lookAt.py
rawls/scene/params.py
rawls/scene/sampler.py
rawls/scene/vector.py
rawls-1.1.7.dist-info/LICENCE
rawls-1.1.7.dist-info/METADATA
rawls-1.1.7.dist-info/WHEEL
rawls-1.1.7.dist-info/top_level.txt
rawls-1.1.7.dist-info/RECORD
