Metadata-Version: 2.1
Name: rawls
Version: 1.1.7
Summary: RAW Light Simulation file reader/converter package
Home-page: https://github.com/prise-3d/rawls
Author: Jérôme BUISINE
Author-email: jerome.buisine@univ-littoral.fr
License: MIT
Platform: UNKNOWN
Classifier: Development Status :: 4 - Beta
Classifier: License :: OSI Approved :: MIT License
Classifier: Programming Language :: Python :: 3.7
Classifier: Topic :: Scientific/Engineering
Classifier: Topic :: Utilities
Requires-Dist: numpy
Requires-Dist: Pillow
Requires-Dist: scipy
Requires-Dist: astropy
Requires-Dist: ipfml
Requires-Dist: pandas
Requires-Dist: OpenEXR
